{"res/atlas/eff/laba.png": "4126f", "p/\u674e\u8d85\u7136.jpg": "62163", "ui/frame.png": "fadb3", "Root.max.html": "b84ff", "p/\u590f\u4e4b\u8424.jpg": "c6f85", "p/\u9093\u4e3d\u840d.jpg": "0ccde", "p/\u5510\u4f1f\u661f.jpg": "66a84", "res/atlas/ui.png": "faca9", "p/\u738b\u8446\u7965.jpg": "c9b1d", "p/\u6d2a\u601d\u658c.jpg": "9fbd2", "res/atlas/comp.png": "4fd0d", "ui/slotmachine.png": "96913", "p/\u5d14\u745e\u950b.jpg": "bdc51", "p/\u7b26\u658c.jpg": "56f8d", "p/\u718a\u5fd7\u5e73.jpg": "436d3", "p/\u6797\u6653\u4f73.jpg": "44957", "p/\u9ec4\u590f\u6167.jpg": "f1e33", "p/\u9648\u6ce2.jpg": "8cef9", "p/\u9a6c\u7406\u4e49.jpg": "fc018", "p/\u5168\u51a0\u6865.jpg": "8a32f", "res/atlas/eff/biao1.png": "8f1fb", "p/\u9ec4\u7430\u601d.jpg": "9862d", "res/atlas/eff/moby1.png": "daee7", "p/\u51af\u51a0\u534e.jpg": "dc0b7", "p/\u9a6c\u8d85.jpg": "6700b", "p/\u738b\u767b\u5b87.jpg": "c760f", "p/\u5218\u4fe1\u8363.jpg": "b79ce", "p/\u5b8b\u4e91\u521a.jpg": "67bc7", "p/\u67f3\u71d5\u98de.jpg": "49a7e", "ui/popBg.png": "d7bb7", "p/\u6234\u8fdc\u5fd7.jpg": "2e0f1", "p/\u9648\u7ae0\u827a.jpg": "7c876", "res/atlas/eff/light.png": "7614d", "p/\u6c6a\u4e3d\u541b.jpg": "fffe9", "ui/inputBg.png": "e50c1", "Root.max.js": "876d4", "p/\u6768\u4f1f\u56fd.jpg": "9e148", "ui/bg.png": "f304a", "p/\u718a\u5175.jpg": "f78f4", "p/default.png": "7a4cb", "p/\u5b81\u534e.jpg": "c812b", "p/\u84dd\u91d1\u660e.jpg": "5378a", "p/\u738b\u51e4\u6b66.jpg": "e5277", "p/\u738b\u5b87\u65b0.jpg": "f40e9", "res/out.tp": "5bd25", "p/\u6731\u5609\u8c6a.jpg": "0fd20", "ver_md5.txt": "8427e", "res/atlas/eff/moby1.atlas": "90a77", "p/\u5468\u7490\u7490.jpg": "aec02", "index.html": "", "p/\u859b\u9e4f\u79d1.jpg": "791a5", "p/\u5218\u6770.jpg": "881b4", "p/\u6e5b\u5b50\u6770.jpg": "da483", "p/\u9ec4\u6c9b.jpg": "2ba4d", "p/\u738b\u741b.jpg": "2c76b", "p/\u5468\u4e50\u5de5.jpg": "97fdf", "res/atlas/eff/yuntian.png": "f3586", "ui/\u62bd\u5956.jpg": "f99cb", "p/\u6881\u666f\u5764.jpg": "5dd06", "p/\u767d\u521a\u7537.jpg": "8c8a6", "p/\u4f55\u6587\u654f.jpg": "e96b0", "res/atlas/eff/sj.png": "ad5c2", "p/\u7f57\u5fd7\u52c7.jpg": "fde6b", "res/atlas/comp.atlas": "6bda3", "ui/xchn.png": "d178b", "p/\u6c6a\u4e9a\u975e.jpg": "54aab", "p/\u66fe\u65e5\u65e5.jpg": "213d4", "p/\u5353\u5609\u8c6a.jpg": "d3bfb", "p/\u5949\u53cc\u559c.jpg": "d922e", "p/\u6768\u4f73\u9633.jpg": "1a83b", "p/\u7f57\u4e16\u541b.jpg": "0a0a8", "unpack.json": "441df", "p/\u90d1\u535a.jpg": "2daf5", "p/\u8303\u8bd7\u5cf0.jpg": "56124", "p/\u9648\u67ef\u68a6.jpg": "e4ad0", "p/\u4faf\u5bb6\u8f89.jpg": "912f5", "p/\u90d1\u8c1a.jpg": "ab464", "p/\u9648\u51ef\u5e73.jpg": "70e4f", "p/\u5f20\u4fca\u5cf0.jpg": "dd180", "res/atlas/ui.atlas": "be0ec", "p/\u5218\u534e\u660e.jpg": "ec781", "p/\u5218\u91d1\u840d.jpg": "59634", "p/\u5b8b\u660e.jpg": "0816e", "version.json": "ae93b", "res/atlas/eff/yuntian.atlas": "8e261", "p/\u674e\u6653\u5f66.jpg": "69477", "p/\u5409\u94f6\u6d01.jpg": "2bb93", "res/atlas/eff/biao1.atlas": "0e2d6", "p/\u4f55\u671d\u9633.jpg": "41e58", "res/atlas/eff/light.atlas": "cb4b0", "p/\u9648\u4e45\u9633.jpg": "378f4", "p/\u9648\u7acb\u79d1.jpg": "0868b", "p/\u9a6c\u9759\u6d9b.jpg": "87d51", "res/atlas/.rec": "f1f79", "res/atlas/eff/sj.atlas": "e371e", "res/atlas/eff/laba.atlas": "40b64", "p/\u90b9\u56fd\u8f89.jpg": "37f0f", "p/\u7b26\u4e16\u9f99.jpg": "6388e", "p/\u674e\u5c1a\u535a.jpg": "6fc51", "p/\u5085\u6d0b.jpg": "308d5", "p/\u5218\u660e\u541b.jpg": "b5051", "p/\u5218\u4fca\u5947.jpg": "6c40e", "p/\u9ece\u9a8f\u6797.jpg": "c4071", "p/\u97e6\u5b9b\u541f.jpg": "d13b6", "p/\u8d75\u6668\u5149.jpg": "1f577", "p/\u6734\u6cf0\u5149.jpg": "cb6ca"}